nagra/__init__.py
nagra/__main__.py
nagra/cli.py
nagra/copy.py
nagra/delete.py
nagra/exceptions.py
nagra/misc.py
nagra/schema.py
nagra/select.py
nagra/sexpr.py
nagra/statement.py
nagra/table.py
nagra/transaction.py
nagra/update.py
nagra/upsert.py
nagra/utils.py
nagra/view.py
nagra/writer.py
nagra/template/duckdb/add_foreign_key.sql
nagra/template/duckdb/create_table.sql
nagra/template/duckdb/create_unique_index.sql
nagra/template/duckdb/debug.sql
nagra/template/duckdb/delete-with-join.sql
nagra/template/duckdb/delete.sql
nagra/template/duckdb/select.sql
nagra/template/duckdb/select_foreign_keys.sql
nagra/template/duckdb/upsert.sql
nagra/template/misc/pydantic-schema.py
nagra/template/misc/schema.d2
nagra/template/misc/schema.toml
nagra/template/postgresql/add_column.sql
nagra/template/postgresql/add_foreign_key.sql
nagra/template/postgresql/create_table.sql
nagra/template/postgresql/create_table_nk.sql
nagra/template/postgresql/create_unique_index.sql
nagra/template/postgresql/create_view.sql
nagra/template/postgresql/debug.sql
nagra/template/postgresql/delete-with-join.sql
nagra/template/postgresql/delete.sql
nagra/template/postgresql/drop_fk.sql
nagra/template/postgresql/drop_table.sql
nagra/template/postgresql/find_columns.sql
nagra/template/postgresql/find_foreign_keys.sql
nagra/template/postgresql/find_index_columns.sql
nagra/template/postgresql/find_indexes.sql
nagra/template/postgresql/find_primary_keys.sql
nagra/template/postgresql/find_unique_constraint.sql
nagra/template/postgresql/find_views.sql
nagra/template/postgresql/select.sql
nagra/template/postgresql/update.sql
nagra/template/postgresql/upsert.sql
nagra/template/sqlite/add_column.sql
nagra/template/sqlite/create_table.sql
nagra/template/sqlite/create_table_nk.sql
nagra/template/sqlite/create_unique_index.sql
nagra/template/sqlite/create_view.sql
nagra/template/sqlite/debug.sql
nagra/template/sqlite/delete-with-join.sql
nagra/template/sqlite/delete.sql
nagra/template/sqlite/drop_table.sql
nagra-0.8.1.dist-info/licenses/LICENSE
nagra-0.8.1.dist-info/METADATA
nagra-0.8.1.dist-info/WHEEL
nagra-0.8.1.dist-info/entry_points.txt
nagra-0.8.1.dist-info/top_level.txt
nagra-0.8.1.dist-info/RECORD
