Metadata-Version: 2.4
Name: nagra
Version: 0.8.1
Summary: Nagra is a Python database toolkit
Project-URL: Homepage, https://github.com/b12consulting/nagra
Requires-Python: >=3.10
License-File: LICENSE
Requires-Dist: jinja2
Requires-Dist: rich
Requires-Dist: toml
Provides-Extra: pandas
Requires-Dist: pandas; extra == "pandas"
Provides-Extra: polars
Requires-Dist: polars; extra == "polars"
Provides-Extra: pg
Requires-Dist: psycopg; extra == "pg"
Provides-Extra: all
Requires-Dist: nagra[pandas,pg,polars]; extra == "all"
Dynamic: license-file
